[
  {
    "date": "2023.11.09",
    "content": [
      {
        "name": "首页增加了一个动画",
        "info": [
          "呃 . . . 虽然早就加好了，但我没更新",
          "这个动画虽然一直在往同一个方向动，但它是无限的",
          "但我并不想拿它当首页",
          "那首页做点什么好呢？@_@"
        ]
      },
      {
        "name": "日记变日志",
        "info": [
          "日记咋能*奔呢，你说对吧",
          "所以这个 select 被单独提出来作为选择界面了",
          "所以里头专对日志的逻辑得改",
          "内容如果不再是根据时间分类的，那就得大改"
        ]
      },
      "主题颜色全改。去掉了饱和度，黑版跟 chrome 默认颜色保持一致，看起来很舒适",
      "路由切换动画改版，用了mode=\"out-in\" 哇塞爽啊"
    ]
  }
]
